tree_sitter_hcl/__init__.py
tree_sitter_hcl/__init__.pyi
tree_sitter_hcl/_binding.pyd
tree_sitter_hcl/binding.c
tree_sitter_hcl/py.typed
tree_sitter_hcl-1.2.0.dist-info/licenses/LICENSE
tree_sitter_hcl-1.2.0.dist-info/METADATA
tree_sitter_hcl-1.2.0.dist-info/WHEEL
tree_sitter_hcl-1.2.0.dist-info/top_level.txt
tree_sitter_hcl-1.2.0.dist-info/RECORD
