Metadata-Version: 2.4
Name: tree-sitter-hcl
Version: 1.2.0
Summary: HCL and terraform grammar for tree-sitter
License: Apache-2.0
Project-URL: Homepage, https://github.com/tree-sitter-grammars/tree-sitter-hcl
Keywords: incremental,parsing,tree-sitter,hcl
Classifier: Intended Audience :: Developers
Classifier: Topic :: Software Development :: Compilers
Classifier: Topic :: Text Processing :: Linguistic
Classifier: Typing :: Typed
Requires-Python: >=3.10
License-File: LICENSE
Provides-Extra: core
Requires-Dist: tree-sitter~=0.24; extra == "core"
Dynamic: license-file
